tera_utils/__init__.py
tera_utils/consol.py
tera_utils/date.py
tera_utils/locals.py
tera_utils/search.py
tera_utils/sort.py
tera_utils/table.py
tera_utils/terminal.py
tera_utils-0.0.3.dist-info/LICENSE.md
tera_utils-0.0.3.dist-info/METADATA
tera_utils-0.0.3.dist-info/WHEEL
tera_utils-0.0.3.dist-info/top_level.txt
tera_utils-0.0.3.dist-info/RECORD
